{
    "JobEfficiency": {
        "aggregate_schema": "modw_aggregates",
        "aggregate_table_alias": "agg",
        "aggregate_table_prefix": "jobefficiency_by_",
        "datasource": "SUPREMM",
        "group_bys": {
            "$ref": "datawarehouse.d/ref/job-efficiency-group-bys.json"
        },
        "name": "JobEfficiency",
        "order": 50,
        "show_in_catalog": false,
        "statistics": {
            "$ref": "datawarehouse.d/ref/job-efficiency-statistics.json"
        }
    }
}
