{
    "application": {
        "attribute_table_schema": "modw_supremm",
        "attribute_to_aggregate_table_key_map": [
            {
                "id": "application_id"
            }
        ],
        "attribute_values_query": {
            "joins": [
                {
                    "name": "application"
                }
            ],
            "orderby": [
                "name"
            ],
            "records": {
                "id": "id",
                "name": "name",
                "order_id": "id",
                "short_name": "name"
            },
            "where": [
                "license_type = 'permissive'"
            ]
        },
        "category": "Executable",
        "chart_options": {
            "dataset_display_type": {
                "aggregate": "h_bar"
            }
        },
        "description_html": "The classication of the job as common scientific application.",
        "name": "Application"
    },
    "day": {
        "$ref": "datawarehouse.d/ref/group-by-time-period.json#/day"
    },
    "exit_status": {
        "attribute_table_schema": "modw_supremm",
        "attribute_to_aggregate_table_key_map": [
            {
                "id": "exit_status_id"
            }
        ],
        "attribute_values_query": {
            "joins": [
                {
                    "name": "exit_status"
                }
            ],
            "orderby": [
                "name"
            ],
            "records": {
                "id": "id",
                "name": "name",
                "order_id": "id",
                "short_name": "name"
            }
        },
        "category": "Executable",
        "chart_options": {
            "dataset_display_type": {
                "aggregate": "bar"
            }
        },
        "data_sort_order": null,
        "description_html": "A categorization of jobs into discrete groups based on the exit status of each job reported by the resource manager.",
        "name": "Exit Status"
    },
    "fieldofscience": {
        "$ref": "datawarehouse.d/ref/group-by-hierarchy.json#/fieldofscience"
    },
    "granted_pe": {
        "attribute_table_schema": "modw_supremm",
        "attribute_to_aggregate_table_key_map": [
            {
                "id": "granted_pe"
            }
        ],
        "attribute_values_query": {
            "joins": [
                {
                    "name": "granted_pe"
                }
            ],
            "orderby": [
                "id"
            ],
            "records": {
                "id": "id",
                "name": "name",
                "order_id": "id",
                "short_name": "name"
            }
        },
        "category": "Usage",
        "chart_options": {
            "dataset_display_type": {
                "aggregate": "h_bar"
            }
        },
        "description_html": "How many cores within one node.",
        "name": "Granted Processing Element"
    },
    "homogeneity_bucket_id": {
        "attribute_table_schema": "modw_supremm",
        "attribute_to_aggregate_table_key_map": [
            {
                "id": "catastrophe_bucket_id"
            }
        ],
        "attribute_values_query": {
            "joins": [
                {
                    "name": "catastrophe_buckets"
                }
            ],
            "orderby": [
                "id"
            ],
            "records": {
                "id": "id",
                "name": "h_description",
                "order_id": "id",
                "short_name": "h_description"
            }
        },
        "category": "Metrics",
        "chart_options": {
            "combine_method": "stack",
            "dataset_display_type": {
                "aggregate": "bar"
            },
            "dataset_type": "aggregate"
        },
        "data_sort_order": null,
        "description_html": "The homogeneity is a measure of the how uniform the L1D load rate is over the lifetime of a job. Jobs with low homogeneity value (near 0) should be investigated to check if an error has caused data processing to stop prematurely.",
        "name": "Homogeneity Rank",
        "show_all_dimension_values": true
    },
    "institution": {
        "attribute_table_schema": "modw",
        "attribute_to_aggregate_table_key_map": [
            {
                "id": "person_organization_id"
            }
        ],
        "attribute_values_query": {
            "joins": [
                {
                    "name": "organization"
                }
            ],
            "orderby": [
                "id"
            ],
            "records": {
                "id": "id",
                "name": "long_name",
                "order_id": "id",
                "short_name": "short_name"
            }
        },
        "category": "Administrative",
        "chart_options": {
            "dataset_display_type": {
                "aggregate": "datasheet"
            },
            "dataset_type": "aggregate"
        },
        "description_html": "Organizations that have users with allocations.",
        "name": "User Institution"
    },
    "jobsize": {
        "$ref": "datawarehouse.d/ref/group-by-common.json#/jobsize"
    },
    "jobwalltime": {
        "$overwrite": {
            "attribute_to_aggregate_table_key_map": [
                {
                    "id": "jobtime_id"
                }
            ]
        },
        "$ref-with-overwrite": "datawarehouse.d/ref/group-by-common.json#/jobwalltime"
    },
    "month": {
        "$ref": "datawarehouse.d/ref/group-by-time-period.json#/month"
    },
    "nodecount": {
        "$overwrite": {
            "attribute_to_aggregate_table_key_map": [
                {
                    "id": "nodecount_id"
                }
            ]
        },
        "$ref-with-overwrite": "datawarehouse.d/ref/group-by-common.json#/nodecount"
    },
    "none": {
        "$overwrite": {
            "attribute_values_query": {
                "joins": [
                    {
                        "name": "dual"
                    }
                ],
                "records": {
                    "id": "-9999",
                    "name": "'${REALM_NAME}'",
                    "order_id": "'${REALM_NAME}'",
                    "short_name": "'${REALM_NAME}'"
                }
            },
            "description_html": "Summarizes job performance data obtained via the SUPReMM project. These data are obtained from performance monitoring software running on each HPC resource. For most resources this data is generated for both XSEDE and non-XSEDE jobs. Non-XSEDE jobs can be filtered using a filter on the \"Grant Type\".",
            "name": "${REALM_NAME}"
        },
        "$ref-with-overwrite": "datawarehouse.d/ref/group-by-none.json"
    },
    "nsfdirectorate": {
        "$ref": "datawarehouse.d/ref/group-by-hierarchy.json#/nsfdirectorate"
    },
    "parentscience": {
        "$ref": "datawarehouse.d/ref/group-by-hierarchy.json#/parentscience"
    },
    "person": {
        "$ref": "datawarehouse.d/ref/group-by-common.json#/person"
    },
    "pi": {
        "$ref": "datawarehouse.d/ref/group-by-common.json#/pi"
    },
    "pi_institution": {
        "attribute_table_schema": "modw",
        "attribute_to_aggregate_table_key_map": [
            {
                "id": "piperson_organization_id"
            }
        ],
        "attribute_values_query": {
            "joins": [
                {
                    "name": "organization"
                }
            ],
            "orderby": [
                "id"
            ],
            "records": {
                "id": "id",
                "name": "long_name",
                "order_id": "id",
                "short_name": "short_name"
            }
        },
        "category": "Administrative",
        "chart_options": {
            "dataset_display_type": {
                "aggregate": "datasheet"
            },
            "dataset_type": "aggregate"
        },
        "description_html": "Organizations that have PIs with allocations.",
        "name": "PI Institution"
    },
    "provider": {
        "$overwrite": {
            "attribute_to_aggregate_table_key_map": [
                {
                    "organization_id": "organization_id"
                }
            ]
        },
        "$ref-with-overwrite": "datawarehouse.d/ref/group-by-common.json#/provider"
    },
    "quarter": {
        "$ref": "datawarehouse.d/ref/group-by-time-period.json#/quarter"
    },
    "queue": {
        "additional_join_constraints": [
            {
                "aggregate_expr": "resource_id",
                "attribute_expr": "resource_id",
                "operation": "="
            }
        ],
        "attribute_table_schema": "modw",
        "attribute_to_aggregate_table_key_map": [
            {
                "id": "queue_id"
            }
        ],
        "attribute_values_query": {
            "joins": [
                {
                    "name": "queue"
                }
            ],
            "orderby": [
                "id"
            ],
            "query_hint": "DISTINCT",
            "records": {
                "id": "id",
                "name": "id",
                "order_id": "id",
                "short_name": "id"
            }
        },
        "chart_options": {
            "dataset_display_type": {
                "aggregate": "h_bar"
            },
            "dataset_type": "aggregate"
        },
        "category": "Usage",
        "description_html": "Queue pertains to the low level job queues on each resource.",
        "name": "Queue"
    },
    "resource": {
        "attribute_table_schema": "modw",
        "attribute_to_aggregate_table_key_map": [
            {
                "id": "resource_id"
            }
        ],
        "attribute_values_query": {
            "joins": [
                {
                    "alias": "rf",
                    "name": "resourcefact"
                },
                {
                    "alias": "rs",
                    "name": "resourcespecs",
                    "on": "rf.id = rs.resource_id"
                }
            ],
            "orderby": [
                "rf.code",
                "rf.name"
            ],
            "records": {
                "id": "rf.id",
                "name": "REPLACE(rf.code, '-', ' ')",
                "order_id": "id",
                "short_name": "REPLACE(rf.code, '-', ' ')"
            },
            "where": [
                "rs.processors IS NOT NULL"
            ]
        },
        "chart_options": {
            "dataset_display_type": {
                "aggregate": "h_bar"
            },
            "dataset_type": "aggregate"
        },
        "category": "Administrative",
        "description_html": "A resource is a remote computer that can run jobs.",
        "name": "Resource"
    },
    "shared": {
        "attribute_table_schema": "modw_supremm",
        "attribute_to_aggregate_table_key_map": [
            {
                "id": "shared"
            }
        ],
        "attribute_values_query": {
            "joins": [
                {
                    "name": "shared"
                }
            ],
            "orderby": [
                "id"
            ],
            "records": {
                "id": "id",
                "name": "name",
                "order_id": "id",
                "short_name": "name"
            }
        },
        "chart_options": {
            "dataset_display_type": {
                "aggregate": "bar"
            }
        },
        "data_sort_order": null,
        "category": "Usage",
        "description_html": "A categorization of jobs into discrete groups based on whether the job shared nodes.",
        "name": "Share Mode"
    },
    "username": {
        "$ref": "datawarehouse.d/ref/group-by-common.json#/username"
    },
    "year": {
        "$ref": "datawarehouse.d/ref/group-by-time-period.json#/year"
    }
}
